plover_dani_machine/__init__.py
plover_dani_machine/dani_key_en.py
plover_dani_machine-0.1.0.dist-info/METADATA
plover_dani_machine-0.1.0.dist-info/WHEEL
plover_dani_machine-0.1.0.dist-info/entry_points.txt
plover_dani_machine-0.1.0.dist-info/top_level.txt
plover_dani_machine-0.1.0.dist-info/RECORD
