Metadata-Version: 2.2
Name: plover-dani-machine
Version: 0.1.0
Summary: My custom Plover machine using the English alphabet
Author: Your Name
Classifier: Programming Language :: Python :: 3
Classifier: License :: OSI Approved :: MIT License
Requires-Python: >=3.7
Requires-Dist: plover>=4.0.0
Dynamic: author
Dynamic: classifier
Dynamic: requires-dist
Dynamic: requires-python
Dynamic: summary
